fastapi_jwt_login/__init__.py
fastapi_jwt_login-0.1.1.dist-info/LICENSE
fastapi_jwt_login-0.1.1.dist-info/METADATA
fastapi_jwt_login-0.1.1.dist-info/WHEEL
fastapi_jwt_login-0.1.1.dist-info/RECORD
