Metadata-Version: 2.1
Name: fastapi-jwt-login
Version: 0.1.1
Summary: 
Author: Michael Piccirillo
Author-email: 70709374+Khrysys@users.noreply.github.com
Requires-Python: >=3.8,<4.0
Classifier: Programming Language :: Python :: 3
Classifier: Programming Language :: Python :: 3.8
Classifier: Programming Language :: Python :: 3.9
Classifier: Programming Language :: Python :: 3.10
Classifier: Programming Language :: Python :: 3.11
Requires-Dist: fastapi (>=0.95.1,<0.96.0)
Requires-Dist: passlib (>=1.7.4,<2.0.0)
Requires-Dist: python-jose[cryptography] (>=3.3.0,<4.0.0)
